paper2data/__init__.py
paper2data/__main__.py
paper2data/advanced_figure_processor.py
paper2data/api_integration.py
paper2data/bibliographic_parser.py
paper2data/citation_network_analyzer.py
paper2data/config_manager.py
paper2data/config_schema.py
paper2data/config_validator.py
paper2data/enhanced_metadata_v1_1.py
paper2data/equation_processor.py
paper2data/extractor.py
paper2data/help_system.py
paper2data/ingest.py
paper2data/integration_test_enhanced_plugin_system.py
paper2data/integration_test_multi_format.py
paper2data/main.py
paper2data/metadata_extractor.py
paper2data/multi_format_exporter.py
paper2data/output_formatters.py
paper2data/performance.py
paper2data/plugin_dependency_manager.py
paper2data/plugin_hooks.py
paper2data/plugin_manager.py
paper2data/plugin_marketplace.py
paper2data/plugin_system_enhanced.py
paper2data/smart_defaults.py
paper2data/table_processor.py
paper2data/test_multi_format_export.py
paper2data/test_plugin_system_enhanced.py
paper2data/utils.py
paper2data/plugins/latex_plugin.py
paper2data/plugins/nlp_plugin.py
paper2data_parser-1.1.2.dist-info/licenses/LICENSE
paper2data_parser-1.1.2.dist-info/METADATA
paper2data_parser-1.1.2.dist-info/WHEEL
paper2data_parser-1.1.2.dist-info/top_level.txt
paper2data_parser-1.1.2.dist-info/RECORD
