Metadata-Version: 2.4
Name: paper2data-parser
Version: 1.1.2
Summary: PDF parsing and content extraction for academic papers
Author-email: Paper2Data Team <team@paper2data.dev>
License: MIT License
Project-URL: Homepage, https://github.com/paper2data/paper2data
Project-URL: Repository, https://github.com/paper2data/paper2data
Project-URL: Documentation, https://paper2data.readthedocs.io
Project-URL: Bug Tracker, https://github.com/paper2data/paper2data/issues
Classifier: Development Status :: 4 - Beta
Classifier: Intended Audience :: Science/Research
Classifier: License :: OSI Approved :: MIT License
Classifier: Programming Language :: Python :: 3
Classifier: Programming Language :: Python :: 3.10
Classifier: Programming Language :: Python :: 3.11
Classifier: Programming Language :: Python :: 3.12
Classifier: Topic :: Scientific/Engineering
Classifier: Topic :: Text Processing :: Markup
Requires-Python: >=3.10
License-File: LICENSE
Requires-Dist: PyMuPDF>=1.23.0
Requires-Dist: pdfplumber>=0.9.0
Requires-Dist: requests>=2.31.0
Requires-Dist: beautifulsoup4>=4.12.0
Requires-Dist: pyyaml>=6.0
Requires-Dist: pillow>=10.0.0
Requires-Dist: lxml>=4.9.0
Requires-Dist: arxiv>=1.4.0
Requires-Dist: feedparser>=6.0.0
Requires-Dist: ratelimit>=2.2.0
Requires-Dist: cachetools>=5.3.0
Requires-Dist: python-dateutil>=2.8.0
Requires-Dist: psutil>=5.9.0
Requires-Dist: networkx>=3.0
Requires-Dist: numpy>=1.24.0
Requires-Dist: pydantic>=2.0.0
Requires-Dist: inquirer>=3.0.0
Requires-Dist: semver>=3.0.0
Requires-Dist: schedule>=1.2.0
Requires-Dist: aiohttp>=3.8.0
Requires-Dist: packaging>=21.0
Provides-Extra: dev
Requires-Dist: pytest>=7.0.0; extra == "dev"
Requires-Dist: pytest-cov>=4.0.0; extra == "dev"
Requires-Dist: black>=23.0.0; extra == "dev"
Requires-Dist: flake8>=6.0.0; extra == "dev"
Requires-Dist: mypy>=1.5.0; extra == "dev"
Requires-Dist: pre-commit>=3.0.0; extra == "dev"
Dynamic: license-file
